{
  "symbol": "KEYS",
  "name": "Keysight Technologies",
  "cik": "0001601046",
  "years": [
    2020,
    2021,
    2022,
    2023,
    2024
  ],
  "yearly_fs": {
    "2020": {
      "revenue": 4221000000.0,
      "operating_income": 765000000.0,
      "rnd_expense": 715000000.0,
      "sga_expense": 1097000000.0,
      "interest_expense": 78000000.0,
      "income_tax_expense": 134000000.0,
      "total_assets": 7218000000.0,
      "total_liabilities": 3921000000.0,
      "total_equity": 3297000000.0,
      "current_assets": 3374000000.0,
      "current_liabilities": 1081000000.0,
      "cash_and_equiv": 1756000000.0,
      "long_term_debt": 1789000000.0,
      "accounts_receivable": 606000000.0,
      "inventory": 757000000.0,
      "ppe": 595000000.0,
      "goodwill": 1537000000.0,
      "cfo": 1016000000.0,
      "cfi": -442000000.0,
      "cff": -413000000.0,
      "capex": 117000000.0,
      "share_repurchases": 411000000.0
    },
    "2021": {
      "revenue": 4941000000.0,
      "operating_income": 1080000000.0,
      "rnd_expense": 811000000.0,
      "sga_expense": 1195000000.0,
      "interest_expense": 79000000.0,
      "income_tax_expense": 116000000.0,
      "total_assets": 7781000000.0,
      "total_liabilities": 3997000000.0,
      "total_equity": 3784000000.0,
      "current_assets": 3834000000.0,
      "current_liabilities": 1309000000.0,
      "cash_and_equiv": 2052000000.0,
      "long_term_debt": 1791000000.0,
      "accounts_receivable": 735000000.0,
      "inventory": 777000000.0,
      "ppe": 650000000.0,
      "goodwill": 1628000000.0,
      "cfo": 1322000000.0,
      "cfi": -353000000.0,
      "cff": -671000000.0,
      "capex": 174000000.0,
      "share_repurchases": 673000000.0
    },
    "2022": {
      "revenue": 5420000000.0,
      "operating_income": 1334000000.0,
      "net_income": 1124000000.0,
      "rnd_expense": 841000000.0,
      "sga_expense": 1283000000.0,
      "interest_expense": 79000000.0,
      "income_tax_expense": 161000000.0,
      "total_assets": 8098000000.0,
      "total_liabilities": 3937000000.0,
      "total_equity": 4161000000.0,
      "current_assets": 4234000000.0,
      "current_liabilities": 1407000000.0,
      "cash_and_equiv": 2042000000.0,
      "short_term_debt": 0.0,
      "long_term_debt": 1793000000.0,
      "accounts_receivable": 905000000.0,
      "inventory": 858000000.0,
      "ppe": 690000000.0,
      "goodwill": 1582000000.0,
      "cfo": 1144000000.0,
      "cfi": -251000000.0,
      "cff": -861000000.0,
      "capex": 185000000.0,
      "share_repurchases": 849000000.0
    },
    "2023": {
      "revenue": 5464000000.0,
      "operating_income": 1358000000.0,
      "net_income": 1057000000.0,
      "rnd_expense": 882000000.0,
      "sga_expense": 1307000000.0,
      "interest_expense": 78000000.0,
      "income_tax_expense": 300000000.0,
      "total_assets": 8683000000.0,
      "total_liabilities": 4029000000.0,
      "total_equity": 4654000000.0,
      "current_assets": 4809000000.0,
      "current_liabilities": 2049000000.0,
      "cash_and_equiv": 2472000000.0,
      "short_term_debt": 599000000.0,
      "long_term_debt": 1195000000.0,
      "accounts_receivable": 900000000.0,
      "inventory": 985000000.0,
      "ppe": 761000000.0,
      "goodwill": 1640000000.0,
      "cfo": 1408000000.0,
      "cfi": -288000000.0,
      "cff": -687000000.0,
      "capex": 197000000.0,
      "share_repurchases": 702000000.0
    },
    "2024": {
      "revenue": 4979000000.0,
      "operating_income": 833000000.0,
      "net_income": 614000000.0,
      "rnd_expense": 919000000.0,
      "sga_expense": 1395000000.0,
      "interest_expense": 84000000.0,
      "income_tax_expense": 251000000.0,
      "total_assets": 9269000000.0,
      "total_liabilities": 4164000000.0,
      "total_equity": 5105000000.0,
      "current_assets": 4257000000.0,
      "current_liabilities": 1427000000.0,
      "cash_and_equiv": 1796000000.0,
      "short_term_debt": 0.0,
      "long_term_debt": 1790000000.0,
      "accounts_receivable": 857000000.0,
      "inventory": 1022000000.0,
      "ppe": 774000000.0,
      "goodwill": 2388000000.0,
      "cfo": 1052000000.0,
      "cfi": -819000000.0,
      "cff": -913000000.0,
      "capex": 154000000.0,
      "share_repurchases": 439000000.0
    }
  }
}